MANIFEST.in
README.rst
pyproject.toml
setup.cfg
setup.py
django_tasks/__init__.py
django_tasks/admin.py
django_tasks/apps.py
django_tasks/models.py
django_tasks/tests.py
django_tasks/urls.py
django_tasks/views.py
django_tasks/migrations/0001_initial.py
django_tasks/migrations/__init__.py
django_tasks/static/tasksapp/style.css
django_tasks/templates/tasksapp/addsubtask.html
django_tasks/templates/tasksapp/addtask.html
django_tasks/templates/tasksapp/home.html
django_tasks/templates/tasksapp/viewtask.html
make_todo.egg-info/PKG-INFO
make_todo.egg-info/SOURCES.txt
make_todo.egg-info/dependency_links.txt
make_todo.egg-info/requires.txt
make_todo.egg-info/top_level.txt